Metadata-Version: 1.0
Name: vslack
Version: 1.3.1
Summary: Vendasta's open source Slack library that makes dealing with incoming webhooks much easier
Home-page: https://github.com/vendasta/vslack.git
Author: Vendasta Technologies
Author-email: gholtslander@vendasta.com
License: apache2
Platform: UNKNOWN
